goedwig/__init__.py
goedwig/cypher.py
goedwig/query.py
goedwig/tag.py
goedwig/version.py
goedwig-0.2.0.dist-info/LICENSE
goedwig-0.2.0.dist-info/METADATA
goedwig-0.2.0.dist-info/WHEEL
goedwig-0.2.0.dist-info/top_level.txt
goedwig-0.2.0.dist-info/RECORD
