Metadata-Version: 2.1
Name: goedwig
Version: 0.2.0
Summary: A generic query engine for graph data, based on abstract syntax trees as input.
Home-page: https://github.com/DerwenAI/goedwig
Author: Paco Nathan
Author-email: paco@derwen.ai
License: MIT
Project-URL: Source Code, https://github.com/DerwenAI/goedwig
Project-URL: Issue Tracker, https://github.com/DerwenAI/goedwig/issues
Keywords: cypher,query optimization,graph query,knowledge graph
Platform: UNKNOWN
Classifier: Programming Language :: Python :: 3
Classifier: License :: OSI Approved :: MIT License
Classifier: Operating System :: OS Independent
Classifier: Development Status :: 5 - Production/Stable
Classifier: Intended Audience :: Developers
Classifier: Intended Audience :: Education
Classifier: Intended Audience :: Information Technology
Classifier: Intended Audience :: Science/Research
Classifier: Topic :: Scientific/Engineering :: Artificial Intelligence
Classifier: Topic :: Scientific/Engineering :: Human Machine Interfaces
Classifier: Topic :: Scientific/Engineering :: Information Analysis
Requires-Python: >=3.8
License-File: LICENSE
Requires-Dist: icecream (>=2.1)
Provides-Extra: base
Requires-Dist: icecream (>=2.1) ; extra == 'base'
Provides-Extra: docs
Requires-Dist: bandit (>=1.7) ; extra == 'docs'
Requires-Dist: codespell (>=2.1) ; extra == 'docs'
Requires-Dist: mypy (>=0.910) ; extra == 'docs'
Requires-Dist: pre-commit (>=2.13) ; extra == 'docs'
Requires-Dist: pylint (>=2.9) ; extra == 'docs'
Requires-Dist: pytest (>=5.4) ; extra == 'docs'
